MANIFEST.in
setup.py
owasp_skf.egg-info/PKG-INFO
owasp_skf.egg-info/SOURCES.txt
owasp_skf.egg-info/dependency_links.txt
owasp_skf.egg-info/requires.txt
owasp_skf.egg-info/top_level.txt
skf/schema.sql
skf/skf.db
skf/skf.py
skf/test_skf.py
skf/version.txt
skf/logs/readme.txt
skf/markdown/checklists/184--ASVS-level-2--0-- 21.56.46.md
skf/markdown/checklists/185--ASVS-level-2--161--ygb-- 21.56.46.md
skf/markdown/checklists/186--ASVS-level-2--162--gb-- 21.56.46.md
skf/markdown/checklists/187--ASVS-level-2--163--gb-- 21.56.46.md
skf/markdown/checklists/188--ASVS-level-2--206--gb-- 21.56.46.md
skf/markdown/checklists/189--ASVS-level-2--185--gb-- 21.56.46.md
skf/markdown/checklists/190--ASVS-level-2--74--gb-- 21.56.46.md
skf/markdown/checklists/191--ASVS-level-2--0-- 21.56.46.md
skf/markdown/checklists/192--ASVS-level-2--45--ygb-- 21.56.46.md
skf/markdown/checklists/193--ASVS-level-2--113--ygb-- 21.56.46.md
skf/markdown/checklists/194--ASVS-level-2--43--ygb-- 21.56.46.md
skf/markdown/checklists/195--ASVS-level-2--114--ygb--.md
skf/markdown/checklists/196--ASVS-level-2--59--ygb--.md
skf/markdown/checklists/197--ASVS-level-2--85--ygb--.md
skf/markdown/checklists/198--ASVS-level-2--86--ygb--.md
skf/markdown/checklists/199--ASVS-level-2--76--gb-- 21.56.46.md
skf/markdown/checklists/200--ASVS-level-2--51--gb-- 21.56.46.md
skf/markdown/checklists/201--ASVS-level-2--122--ygb--.md
skf/markdown/checklists/202--ASVS-level-2--115--ygb--.md
skf/markdown/checklists/203--ASVS-level-2--70--ygb--.md
skf/markdown/checklists/204--ASVS-level-2--63--ygb--.md
skf/markdown/checklists/205--ASVS-level-2--29--ygb--.md
skf/markdown/checklists/206--ASVS-level-2--65--gb-- 21.56.46.md
skf/markdown/checklists/207--ASVS-level-2--115--ygb--.md
skf/markdown/checklists/208--ASVS-level-2--182--gb-- 21.56.46.md
skf/markdown/checklists/209--ASVS-level-2--87--ygb--.md
skf/markdown/checklists/210--ASVS-level-2--88--gb-- 21.56.46.md
skf/markdown/checklists/211--ASVS-level-2--86--gb-- 21.56.46.md
skf/markdown/checklists/212--ASVS-level-2--59--ygb--.md
skf/markdown/checklists/213--ASVS-level-2--74--ygb--.md
skf/markdown/checklists/214--ASVS-level-2--186--gb-- 21.56.46.md
