Metadata-Version: 1.1
Name: owasp-skf
Version: 1.3.21
Summary: The OWASP Security Knowledge Framework
Home-page: https://github.com/blabla1337/skf-flask
Author: Glenn ten Cate, Riccardo ten Cate
Author-email: gtencate@schubergphilis.com, r.tencate77@gmail.com
License: AGPLV3
Platform: UNKNOWN
Classifier: Development Status :: 5 - Production/Stable
Classifier: Framework :: Flask
Classifier: Environment :: Web Environment
Classifier: Intended Audience :: Developers
Classifier: Intended Audience :: Education
Classifier: Topic :: Software Development
Classifier: Topic :: Security
Classifier: Operating System :: MacOS
Classifier: Operating System :: Microsoft :: Windows
Classifier: Operating System :: Unix
Classifier: Programming Language :: Python :: 2.7
Classifier: License :: OSI Approved :: GNU Affero General Public License v3 or later (AGPLv3+)
